flityard/__init__.py
flityard/main.py
flityard-0.2.0.dist-info/LICENSE
flityard-0.2.0.dist-info/WHEEL
flityard-0.2.0.dist-info/METADATA
flityard-0.2.0.dist-info/RECORD
