Metadata-Version: 2.1
Name: flityard
Version: 0.2.0
Summary: A very simple library.
Home-page: https://github.com/karantan/flityard
License: UNKNOWN
Author: Gasper Vozel
Author-email: karantan@gmail.com
Classifier: License :: OSI Approved :: MIT License
Requires-Dist: requests
